{
  "generated_at": "2026-02-23T01:54:53.762390+00:00",
  "model": "window_mean_diff_permutation_test",
  "interval_note": "placebo_null_ci95 is a placebo/null reference band, not an estimator confidence interval",
  "policy": "strict-balanced",
  "shock_catalog_key": "shock_dates_nonoverlap_30d",
  "observed_days": 12672,
  "status": "ok",
  "reason": "did_estimated",
  "shock_threshold": null,
  "shock_source": "shock_catalog_dates",
  "shock_days": 23,
  "shock_days_used": 23,
  "shock_sampling": "full",
  "windows": {
    "7": {
      "status": "ok",
      "reason": "estimated",
      "att": -25.178452,
      "p_value": 0.997,
      "placebo_null_ci95": [
        -11.022054,
        12.031086
      ],
      "n_obs_events": 20,
      "n_null": 2000
    },
    "14": {
      "status": "ok",
      "reason": "estimated",
      "att": -14.458082,
      "p_value": 0.991,
      "placebo_null_ci95": [
        -10.09248,
        11.657409
      ],
      "n_obs_events": 23,
      "n_null": 2000
    },
    "30": {
      "status": "ok",
      "reason": "estimated",
      "att": -4.864891,
      "p_value": 0.907,
      "placebo_null_ci95": [
        -8.24113,
        8.507945
      ],
      "n_obs_events": 23,
      "n_null": 2000
    }
  },
  "negative_controls": {
    "entertainment": {
      "status": "ok",
      "reason": "estimated",
      "att": 0.006211,
      "p_value": 0.059,
      "placebo_null_ci95": [
        -0.006211,
        0.006211
      ],
      "n_obs_events": 23,
      "n_null": 2000
    },
    "sports": {
      "status": "ok",
      "reason": "estimated",
      "att": 0.0,
      "p_value": 0.9395,
      "placebo_null_ci95": [
        -0.012422,
        0.012578
      ],
      "n_obs_events": 23,
      "n_null": 2000
    },
    "technology": {
      "status": "ok",
      "reason": "estimated",
      "att": -0.012422,
      "p_value": 0.979,
      "placebo_null_ci95": [
        -0.012422,
        0.025
      ],
      "n_obs_events": 23,
      "n_null": 2000
    },
    "weather": {
      "status": "ok",
      "reason": "estimated",
      "att": 0.0,
      "p_value": 0.9575,
      "placebo_null_ci95": [
        -0.012422,
        0.012422
      ],
      "n_obs_events": 23,
      "n_null": 2000
    }
  },
  "gates": {
    "significant_positive_windows": 0,
    "negative_controls_available": true,
    "negative_controls_estimated": 4,
    "negative_control_violations": 0,
    "negative_control_borderline_positives": 1,
    "negative_control_min_effect": 0.05,
    "did_passed": false
  }
}